budgetreport/__init__.py
budgetreport/budget.py
budgetreport/main.py
budgetreport/period.py
budgetreport/report.py
budget_report-0.4.dist-info/LICENSE
budget_report-0.4.dist-info/METADATA
budget_report-0.4.dist-info/WHEEL
budget_report-0.4.dist-info/entry_points.txt
budget_report-0.4.dist-info/top_level.txt
budget_report-0.4.dist-info/RECORD
