Metadata-Version: 2.1
Name: budget-report
Version: 0.4
Summary: Budget report for beancount files
Home-page: http://github.com/sulemankm/budget_report
Author: Suleman Khalid
Author-email: sulemankm@yahoo.com
License: GPL-v3
Project-URL: Bug Tracker, https://github.com/sulemankm/budget_report/issues
Keywords: beancount budget ledger hledger
Platform: UNKNOWN
Requires-Dist: beancount
Requires-Dist: tabulate
